{
  "pmid": "26028915",
  "title": "Reporting results of research involving human subjects: an ethical obligation.",
  "abstract": "Researchers have an ethical responsibility to report the results of research involving human subjects. Dissemination of results ensures that patient care is based on good science and that the field of medicine advances based on complete and accurate knowledge. However, current evidence suggests that publication is often neglected or substantially delayed, especially in the case of negative and inconclusive results. Researchers, editors and reviewers should value all high-quality research regardless of the conclusiveness of the results and ensure that all research involving human subjects is registered in a publicly accessible database.",
  "year": 2015,
  "journal": "Journal of Korean medical science",
  "authors": [
    "Allison Baer Alley",
    "Jeong-Wook Seo",
    "Sung-Tae Hong"
  ],
  "doi": "10.3346/jkms.2015.30.6.673",
  "publication_types": [
    "Journal Article",
    "Review"
  ],
  "mesh_terms": [
    "Clinical Trials as Topic",
    "Ethics, Research",
    "Human Experimentation",
    "Publishing",
    "Republic of Korea",
    "Research Report",
    "Research Subjects"
  ],
  "keywords": [
    "Ethics, Research",
    "Negative Results",
    "Results Reporting",
    "Trial Registration"
  ],
  "affiliations": [
    "JW LEE Center for Global Medicine, Seoul, Korea.",
    "Department of Pathology, Seoul National University College of Medicine, Seoul, Korea.",
    "Department of Parasitology and Tropical Medicine, Seoul National University College of Medicine, Seoul, Korea."
  ]
}